motle/__init__.py
motle/dictionary.py
motle/motle.py
motle/tools.py
motle-0.2.dist-info/LICENSE
motle-0.2.dist-info/METADATA
motle-0.2.dist-info/WHEEL
motle-0.2.dist-info/top_level.txt
motle-0.2.dist-info/RECORD
