Metadata-Version: 2.1
Name: motle
Version: 0.2
Summary: Motle is a library for finding words in wordle game
Home-page: https://github.com/Gokender/motle
Author: Gauthier Chaty
Author-email: gauthier.chaty+pypi@outlook.fr
License: MIT
Platform: UNKNOWN
License-File: LICENSE
